adk_extra_services/__init__.py
adk_extra_services/__version__.py
adk_extra_services/artifacts/__init__.py
adk_extra_services/artifacts/azure_artifact_service.py
adk_extra_services/artifacts/local_folder_artifact_service.py
adk_extra_services/artifacts/s3_artifact_service.py
adk_extra_services/artifacts/supabase_artifact_service.py
adk_extra_services/sessions/__init__.py
adk_extra_services/sessions/mongo_session_service.py
adk_extra_services/sessions/redis_session_service.py
adk_extra_services-0.1.7.dist-info/licenses/LICENSE
adk_extra_services-0.1.7.dist-info/METADATA
adk_extra_services-0.1.7.dist-info/WHEEL
adk_extra_services-0.1.7.dist-info/top_level.txt
adk_extra_services-0.1.7.dist-info/RECORD
