Metadata-Version: 2.4
Name: adk-extra-services
Version: 0.1.7
Summary: Additional service implementations for Google ADK
Author-email: edu010101 <eduardo@geoia.tech>
License: Apache-2.0
Project-URL: Homepage, https://github.com/edu010101/adk-extra-services
Project-URL: Source, https://github.com/edu010101/adk-extra-services
Project-URL: Documentation, https://github.com/edu010101/adk-extra-services#readme
Keywords: adk,google-adk,s3,amazon-s3,artifact-storage,session-service,redis,mongo,supabase
Classifier: Development Status :: 3 - Alpha
Classifier: Intended Audience :: Developers
Classifier: License :: OSI Approved :: Apache Software License
Classifier: Programming Language :: Python :: 3
Classifier: Programming Language :: Python :: 3.8
Classifier: Programming Language :: Python :: 3.9
Classifier: Programming Language :: Python :: 3.10
Classifier: Programming Language :: Python :: 3.11
Classifier: Operating System :: OS Independent
Classifier: Topic :: Software Development :: Libraries :: Python Modules
Requires-Python: >=3.8
License-File: LICENSE
Requires-Dist: google-adk
Requires-Dist: google-generativeai>=0.8.5
Requires-Dist: boto3>=1.28.0
Requires-Dist: typing-extensions>=4.0.0
Requires-Dist: motor>=3.3.0
Requires-Dist: redis>=5.0.0
Requires-Dist: azure-storage-blob>=12.20.0
Requires-Dist: supabase>=2.0.0
Requires-Dist: python-dotenv>=1.0.0
Provides-Extra: dev
Requires-Dist: pytest>=7.0.0; extra == "dev"
Requires-Dist: pytest-asyncio>=0.21.0; extra == "dev"
Requires-Dist: black; extra == "dev"
Requires-Dist: flake8; extra == "dev"
Requires-Dist: mypy; extra == "dev"
Requires-Dist: isort; extra == "dev"
Requires-Dist: python-dotenv>=1.0.0; extra == "dev"
Provides-Extra: test
Requires-Dist: pytest>=8.0.0; extra == "test"
Requires-Dist: pytest-asyncio>=0.25.0; extra == "test"
Requires-Dist: pytest-mock>=3.14.0; extra == "test"
Requires-Dist: testcontainers>=3.10.0; extra == "test"
Provides-Extra: docs
Requires-Dist: sphinx>=7.2.0; extra == "docs"
Requires-Dist: furo>=2023.9.10; extra == "docs"
Requires-Dist: myst-parser>=2.0.0; extra == "docs"
Dynamic: license-file
